parupome/__init__.py
parupome-0.1.dist-info/LICENSE
parupome-0.1.dist-info/METADATA
parupome-0.1.dist-info/WHEEL
parupome-0.1.dist-info/top_level.txt
parupome-0.1.dist-info/RECORD
